chunkifyr/__init__.py
chunkifyr/base.py
chunkifyr/lm_chunker.py
chunkifyr/semantic_chunker.py
chunkifyr/simple_semantic_chunker.py
chunkifyr/simple_syntactic_chunker.py
chunkifyr/syntactic_chunker.py
chunkifyr/util.py
chunkifyr-0.1.2.dist-info/LICENSE
chunkifyr-0.1.2.dist-info/METADATA
chunkifyr-0.1.2.dist-info/WHEEL
chunkifyr-0.1.2.dist-info/top_level.txt
chunkifyr-0.1.2.dist-info/RECORD
