Metadata-Version: 2.1
Name: chunkifyr
Version: 0.1.2
Summary: Your ultimate toolkit for text chunking. 
Home-page: https://github.com/xdevfaheem/chunkifyr
Author: Mohammed Faheem
Author-email: xdevfahem@gmail.com
Project-URL: Bug Tracker, https://github.com/xdevfaheem/chunkifyr/issues
Classifier: Programming Language :: Python :: 3
Classifier: License :: OSI Approved :: MIT License
Classifier: Operating System :: OS Independent
Requires-Python: >=3.9
License-File: LICENSE
Requires-Dist: python-docx
Requires-Dist: PyMuPDF
Requires-Dist: langchain >=2.0
Requires-Dist: instructor
Requires-Dist: spacy
Requires-Dist: transformers
Requires-Dist: tqdm
Requires-Dist: sentence-transformers
Requires-Dist: openai
Provides-Extra: dev
Requires-Dist: pytest >=6.0 ; extra == 'dev'
Requires-Dist: black ; extra == 'dev'
